redis_memory/__init__.py
redis_memory-0.3.4.dist-info/licenses/LICENSE
redis_memory-0.3.4.dist-info/METADATA
redis_memory-0.3.4.dist-info/WHEEL
redis_memory-0.3.4.dist-info/top_level.txt
redis_memory-0.3.4.dist-info/RECORD
